mlx_vlm/__init__.py
mlx_vlm/__main__.py
mlx_vlm/chat.py
mlx_vlm/chat_ui.py
mlx_vlm/convert.py
mlx_vlm/deprecation.py
mlx_vlm/generate.py
mlx_vlm/lora.py
mlx_vlm/prompt_utils.py
mlx_vlm/sample_utils.py
mlx_vlm/server.py
mlx_vlm/smolvlm_video_generate.py
mlx_vlm/tokenizer_utils.py
mlx_vlm/utils.py
mlx_vlm/version.py
mlx_vlm/video_generate.py
mlx_vlm/evals/__init__.py
mlx_vlm/evals/math_vista.py
mlx_vlm/evals/mmmu.py
mlx_vlm/evals/mmstar.py
mlx_vlm/evals/ocrbench.py
mlx_vlm/evals/utils.py
mlx_vlm/models/__init__.py
mlx_vlm/models/base.py
mlx_vlm/models/cache.py
mlx_vlm/models/kernels.py
mlx_vlm/models/aya_vision/__init__.py
mlx_vlm/models/aya_vision/aya_vision.py
mlx_vlm/models/aya_vision/config.py
mlx_vlm/models/aya_vision/interpolate.py
mlx_vlm/models/aya_vision/language.py
mlx_vlm/models/aya_vision/vision.py
mlx_vlm/models/deepseek_vl_v2/__init__.py
mlx_vlm/models/deepseek_vl_v2/config.py
mlx_vlm/models/deepseek_vl_v2/conversation.py
mlx_vlm/models/deepseek_vl_v2/deepseek_vl_v2.py
mlx_vlm/models/deepseek_vl_v2/language.py
mlx_vlm/models/deepseek_vl_v2/processing_deepsek_vl_v2.py
mlx_vlm/models/deepseek_vl_v2/vision.py
mlx_vlm/models/deepseekocr/__init__.py
mlx_vlm/models/deepseekocr/config.py
mlx_vlm/models/deepseekocr/conversation.py
mlx_vlm/models/deepseekocr/deepseekocr.py
mlx_vlm/models/deepseekocr/language.py
mlx_vlm/models/deepseekocr/processing_deepseekocr.py
mlx_vlm/models/deepseekocr/sam.py
mlx_vlm/models/deepseekocr/vision.py
mlx_vlm/models/fastvlm/__init__.py
mlx_vlm/models/fastvlm/config.py
mlx_vlm/models/fastvlm/fastvlm.py
mlx_vlm/models/fastvlm/language.py
mlx_vlm/models/fastvlm/vision.py
mlx_vlm/models/florence2/__init__.py
mlx_vlm/models/florence2/config.py
mlx_vlm/models/florence2/florence2.py
mlx_vlm/models/florence2/language.py
mlx_vlm/models/florence2/vision.py
mlx_vlm/models/gemma3/__init__.py
mlx_vlm/models/gemma3/config.py
mlx_vlm/models/gemma3/gemma3.py
mlx_vlm/models/gemma3/language.py
mlx_vlm/models/gemma3/vision.py
mlx_vlm-0.3.9.dist-info/licenses/LICENSE
mlx_vlm-0.3.9.dist-info/METADATA
mlx_vlm-0.3.9.dist-info/WHEEL
mlx_vlm-0.3.9.dist-info/entry_points.txt
mlx_vlm-0.3.9.dist-info/top_level.txt
mlx_vlm-0.3.9.dist-info/RECORD
