Metadata-Version: 2.4
Name: mlx-vlm
Version: 0.3.9
Summary: MLX-VLM is a package for inference and fine-tuning of Vision Language Models (VLMs) and Omni Models (VLMs with audio and video support) on your Mac using MLX.
Author-email: Prince Canuma <prince.gdt@gmail.com>
License: MIT
Project-URL: Homepage, https://github.com/Blaizzy/mlx-vlm
Project-URL: Repository, https://github.com/Blaizzy/mlx-vlm
Project-URL: Issues, https://github.com/Blaizzy/mlx-vlm/issues
Classifier: Development Status :: 4 - Beta
Classifier: Intended Audience :: Developers
Classifier: License :: OSI Approved :: MIT License
Classifier: Programming Language :: Python :: 3
Classifier: Programming Language :: Python :: 3.8
Classifier: Programming Language :: Python :: 3.9
Classifier: Programming Language :: Python :: 3.10
Classifier: Programming Language :: Python :: 3.11
Classifier: Programming Language :: Python :: 3.12
Requires-Python: >=3.10
License-File: LICENSE
Requires-Dist: mlx>=0.26.0
Requires-Dist: datasets>=2.19.1
Requires-Dist: tqdm>=4.66.2
Requires-Dist: transformers>=4.57.0
Requires-Dist: Pillow>=10.3.0
Requires-Dist: requests>=2.31.0
Requires-Dist: mlx-lm>=0.23.0
Requires-Dist: fastapi>=0.95.1
Requires-Dist: soundfile>=0.13.1
Requires-Dist: opencv-python>=4.12.0.88
Requires-Dist: numpy
Requires-Dist: uvicorn
Provides-Extra: ui
Requires-Dist: gradio>=5.19.0; extra == "ui"
Provides-Extra: audio
Requires-Dist: mlx-audio; extra == "audio"
Provides-Extra: torch
Requires-Dist: torch; extra == "torch"
Requires-Dist: torchvision; extra == "torch"
Requires-Dist: einops; extra == "torch"
Requires-Dist: blobfile; extra == "torch"
Requires-Dist: tiktoken; extra == "torch"
Provides-Extra: cuda
Requires-Dist: mlx-cuda; extra == "cuda"
Provides-Extra: cpu
Requires-Dist: mlx-cpu; extra == "cpu"
Dynamic: license-file
